mkdocs_navsorted/__init__.py
mkdocs_navsorted/plugin.py
mkdocs_navsorted/utils.py
mkdocs_navsorted_plugin-1.0.0.dist-info/METADATA
mkdocs_navsorted_plugin-1.0.0.dist-info/WHEEL
mkdocs_navsorted_plugin-1.0.0.dist-info/entry_points.txt
mkdocs_navsorted_plugin-1.0.0.dist-info/licenses/LICENSE
mkdocs_navsorted_plugin-1.0.0.dist-info/RECORD
