Metadata-Version: 2.4
Name: mkdocs-navsorted-plugin
Version: 1.0.0
Summary: mkdocs plugin to get nav sorted without yml directives
Project-URL: Homepage, https://github.com/idlesign/mkdocs-navsorted-plugin
Project-URL: Documentation, https://mkdocs-navsorted-plugin.readthedocs.org/
Author-email: Igor Starikov <idlesign@yandex.ru>
License-Expression: BSD-3-Clause
License-File: LICENSE
Keywords: mkdocs,navigation,plugin
Requires-Python: >=3.10
Requires-Dist: mkdocs
